bingx_py/__init__.py
bingx_py/asyncio/__init__.py
bingx_py/asyncio/agent.py
bingx_py/asyncio/spot/__init__.py
bingx_py/asyncio/spot/account.py
bingx_py/asyncio/spot/market.py
bingx_py/asyncio/spot/trades.py
bingx_py/asyncio/spot/wallet.py
bingx_py/asyncio/standard.py
bingx_py/asyncio/sub_account.py
bingx_py/asyncio/swap/__init__.py
bingx_py/asyncio/swap/account.py
bingx_py/asyncio/swap/market.py
bingx_py/asyncio/swap/trades.py
bingx_py/caching/__init__.py
bingx_py/caching/base.py
bingx_py/caching/memory_cache.py
bingx_py/caching/redis_cache.py
bingx_py/client/__init__.py
bingx_py/client/agent.py
bingx_py/client/spot/__init__.py
bingx_py/client/spot/account.py
bingx_py/client/spot/market.py
bingx_py/client/spot/trades.py
bingx_py/client/spot/wallet.py
bingx_py/client/standard.py
bingx_py/client/sub_account.py
bingx_py/client/swap/__init__.py
bingx_py/client/swap/account.py
bingx_py/client/swap/market.py
bingx_py/client/swap/trades.py
bingx_py/config.py
bingx_py/exceptions.py
bingx_py/http_client.py
bingx_py/models/__init__.py
bingx_py/models/agent.py
bingx_py/models/general.py
bingx_py/models/spot/__init__.py
bingx_py/models/spot/account.py
bingx_py/models/spot/market.py
bingx_py/models/spot/trades.py
bingx_py/models/spot/wallet.py
bingx_py/models/standard.py
bingx_py/models/sub_account.py
bingx_py/models/swap/__init__.py
bingx_py/models/swap/account.py
bingx_py/models/swap/market.py
bingx_py/models/swap/trades.py
bingx_py-1.0.2.dist-info/LICENCE
bingx_py-1.0.2.dist-info/METADATA
bingx_py-1.0.2.dist-info/WHEEL
bingx_py-1.0.2.dist-info/RECORD
