Metadata-Version: 2.3
Name: bingx-py
Version: 1.0.2
Summary: A python BingX API sync/async client
License: MIT
Author: Daniil Pavlovich
Author-email: layred.dota2@mail.ru
Requires-Python: >=3.10,<4.0
Classifier: License :: OSI Approved :: MIT License
Classifier: Programming Language :: Python :: 3
Classifier: Programming Language :: Python :: 3.10
Classifier: Programming Language :: Python :: 3.11
Classifier: Programming Language :: Python :: 3.12
Classifier: Programming Language :: Python :: 3.13
Requires-Dist: aiohttp (>=3.11.11,<4.0.0)
Requires-Dist: pydantic (>=2.10.5,<3.0.0)
Requires-Dist: redis (>=5.2.1,<6.0.0)
Requires-Dist: requests (>=2.32.3,<3.0.0)
Project-URL: Bug Tracker, https://github.com/vispar-tech/bingx-py/issues
Project-URL: Documentation, https://bingx-py.readthedocs.io/en/latest/
Project-URL: Homepage, https://github.com/vispar-tech/bingx-py
Project-URL: Repository, https://github.com/vispar-tech/bingx-py
